{"branch_id":"dd6dc45c-0587-4053-93b0-095191eefdb2","name":"master","settings":{"physics":{"gravity":[0,-9.8,0]},"render":{"lightmapFilterRange":10,"tonemapping":3,"ambientBakeOcclusionContrast":0,"skybox":93648610,"lightmapFilterSmoothness":0.2,"gamma_correction":1,"fog_start":1,"skyboxIntensity":1,"fog_color":[0,0,0],"lightmapMode":1,"ambientBakeSpherePart":0.4,"fog":"none","lightmapMaxResolution":2048,"skyboxMip":2,"lightmapSizeMultiplier":16,"fog_end":1000,"lightmapFilterEnabled":false,"ambientBake":false,"fog_density":0.01,"exposure":1.2,"global_ambient":[0.2,0.2,0.2],"ambientBakeNumSamples":1,"ambientBakeOcclusionBrightness":0,"skyboxRotation":[0,0,0]}},"entities":{"ad67de32-0ddc-48f6-bb26-745066fee847":{"name":"Root","parent":null,"resource_id":"ad67de32-0ddc-48f6-bb26-745066fee847","tags":[],"enabled":true,"components":{},"scale":[1,1,1],"position":[0,0,0],"rotation":[0,0,0],"children":["126f4838-072c-46f0-8c53-b539d7c94d8f","db0aa378-f896-4c25-8e05-367e6d3a3bae","54d33b96-8f6e-4049-a2f2-820a548b571b","260f8750-9c58-4b82-9ec1-9d67e58a8ee7","775c9b60-931e-4ee0-a139-3320165416d2","8384db28-c61c-45b6-b6fa-858a471a14ce","1d6eae3f-c897-4e7d-852a-95dc5568c93a","26ee7d94-64d6-4a90-8951-a7b5f1db6e9d"]},"54d33b96-8f6e-4049-a2f2-820a548b571b":{"name":"Camera","parent":"ad67de32-0ddc-48f6-bb26-745066fee847","resource_id":"54d33b96-8f6e-4049-a2f2-820a548b571b","tags":["camera"],"enabled":true,"components":{"camera":{"fov":45,"projection":0,"clearColor":[0.118,0.118,0.118,1],"clearColorBuffer":true,"clearDepthBuffer":true,"frustumCulling":true,"enabled":true,"orthoHeight":4,"farClip":1000,"nearClip":0.1,"priority":0,"rect":[0,0,1,1],"layers":[0,1,2,3,4]},"script":{"enabled":true,"order":["orthoCamera"],"scripts":{"orthoCamera":{"enabled":false,"attributes":{"lookAt":null}}}}},"scale":[1,1,1],"position":[15,15,15],"rotation":[-45,45,0],"children":[]},"260f8750-9c58-4b82-9ec1-9d67e58a8ee7":{"name":"Light","parent":"ad67de32-0ddc-48f6-bb26-745066fee847","resource_id":"260f8750-9c58-4b82-9ec1-9d67e58a8ee7","tags":[],"enabled":true,"components":{"light":{"enabled":true,"bake":false,"bakeNumSamples":1,"bakeArea":0,"bakeDir":true,"affectDynamic":true,"affectLightmapped":false,"isStatic":false,"color":[1,1,1],"intensity":1,"type":"directional","shadowDistance":32,"range":8,"innerConeAngle":40,"outerConeAngle":45,"shape":0,"falloffMode":0,"castShadows":true,"shadowUpdateMode":2,"shadowType":0,"shadowResolution":2048,"shadowBias":0.2,"normalOffsetBias":0.05,"vsmBlurMode":1,"vsmBlurSize":11,"vsmBias":0.01,"cookieAsset":null,"cookieIntensity":1,"cookieFalloff":true,"cookieChannel":"rgb","cookieAngle":0,"cookieScale":[1,1],"cookieOffset":[0,0],"layers":[0]}},"scale":[1,1,1],"position":[2,2,-2],"rotation":[-158.28,48.79,171.02],"children":[]},"775c9b60-931e-4ee0-a139-3320165416d2":{"name":"main_ground","parent":"ad67de32-0ddc-48f6-bb26-745066fee847","resource_id":"775c9b60-931e-4ee0-a139-3320165416d2","tags":["ground"],"enabled":true,"components":{"render":{"enabled":true,"type":"plane","asset":null,"materialAssets":[93650576],"castShadows":true,"receiveShadows":true,"lightmapped":false,"lightmapSizeMultiplier":1,"castShadowsLightmap":true,"rootBone":null,"isStatic":false,"layers":[0],"batchGroupId":null},"collision":{"enabled":true,"type":"box","halfExtents":[25,0,25],"radius":0.5,"axis":1,"height":2,"asset":null,"renderAsset":null},"rigidbody":{"enabled":true,"type":"static","mass":1,"linearDamping":0,"angularDamping":0,"linearFactor":[1,1,1],"angularFactor":[1,1,1],"friction":1,"restitution":0}},"scale":[50,1,50],"position":[0,-0.02,0],"rotation":[0,0,0],"children":[]},"8384db28-c61c-45b6-b6fa-858a471a14ce":{"name":"H_ground_carpet","tags":["house_item"],"enabled":true,"resource_id":"8384db28-c61c-45b6-b6fa-858a471a14ce","parent":"ad67de32-0ddc-48f6-bb26-745066fee847","children":["1186fffd-d8a0-4b86-8ac3-5bd60722e0da"],"position":[-0.024888992309570312,-3.552713678800501e-15,0.13261032104492188],"rotation":[0,0,0],"scale":[4,1,4],"components":{"render":{"enabled":true,"type":"plane","asset":null,"materialAssets":[94117503],"layers":[0],"batchGroupId":null,"castShadows":true,"castShadowsLightmap":false,"receiveShadows":true,"lightmapped":false,"lightmapSizeMultiplier":1,"castShadowsLightMap":true,"lightMapped":false,"lightMapSizeMultiplier":1,"isStatic":true,"rootBone":null},"collision":{"enabled":true,"type":"compound","halfExtents":[2,0,2],"radius":0.5,"axis":1,"height":2,"asset":null,"renderAsset":null},"rigidbody":{"enabled":true,"type":"static","mass":1,"linearDamping":0,"angularDamping":0,"linearFactor":[1,1,1],"angularFactor":[1,1,1],"friction":1,"restitution":0}},"template_id":95946170,"template_ent_ids":{"8384db28-c61c-45b6-b6fa-858a471a14ce":"06a09126-da1b-4768-a4c4-48b263255272","1186fffd-d8a0-4b86-8ac3-5bd60722e0da":"b5ff2ea5-eeb5-42c4-81b7-f323a8ca1927"}},"1d6eae3f-c897-4e7d-852a-95dc5568c93a":{"name":"H_prop_table_set_01","tags":["house_item"],"enabled":false,"resource_id":"1d6eae3f-c897-4e7d-852a-95dc5568c93a","parent":"ad67de32-0ddc-48f6-bb26-745066fee847","children":["ab75dbb0-db9c-4572-a876-398ecb7c090a"],"position":[-5,0,-0.5],"rotation":[0,0,0],"scale":[2,2,2],"components":{"model":{"enabled":true,"type":"asset","asset":94102868,"materialAsset":null,"castShadows":true,"castShadowsLightmap":false,"receiveShadows":false,"lightmapped":false,"lightmapSizeMultiplier":1,"castShadowsLightMap":true,"lightMapped":false,"lightMapSizeMultiplier":1,"isStatic":true,"layers":[0],"batchGroupId":null},"rigidbody":{"enabled":true,"type":"static","mass":1,"linearDamping":0,"angularDamping":0,"linearFactor":[1,1,1],"angularFactor":[1,1,1],"friction":1,"restitution":0},"collision":{"enabled":true,"type":"compound","halfExtents":[0.5,0.5,0.5],"radius":0.5,"axis":1,"height":2,"asset":null,"renderAsset":null}},"template_id":95947455,"template_ent_ids":{"1d6eae3f-c897-4e7d-852a-95dc5568c93a":"e9964d79-6dcf-4827-aaa0-2b300137d271","ab75dbb0-db9c-4572-a876-398ecb7c090a":"1349ff0d-cc29-4b1f-9830-08c0e3782609"}},"ab75dbb0-db9c-4572-a876-398ecb7c090a":{"name":"collision","tags":[],"enabled":true,"resource_id":"ab75dbb0-db9c-4572-a876-398ecb7c090a","parent":"1d6eae3f-c897-4e7d-852a-95dc5568c93a","children":[],"position":[0,0.25,0],"rotation":[0,0,0],"scale":[1,1,1],"components":{"collision":{"enabled":true,"type":"box","halfExtents":[1,0.5,0.5],"radius":0.5,"axis":1,"height":2,"asset":null,"renderAsset":null}}},"26ee7d94-64d6-4a90-8951-a7b5f1db6e9d":{"name":"H_prop_ice_set_01","tags":["house_item"],"enabled":false,"resource_id":"26ee7d94-64d6-4a90-8951-a7b5f1db6e9d","parent":"ad67de32-0ddc-48f6-bb26-745066fee847","children":["c621cce9-2059-4dca-a681-b541929dab08"],"position":[-4.5,0,1.5],"rotation":[0,0,0],"scale":[1,1,1],"components":{"model":{"enabled":true,"type":"asset","asset":94102860,"materialAsset":null,"castShadows":true,"castShadowsLightmap":false,"receiveShadows":true,"lightmapped":false,"lightmapSizeMultiplier":1,"castShadowsLightMap":true,"lightMapped":false,"lightMapSizeMultiplier":1,"isStatic":true,"layers":[0],"batchGroupId":null},"rigidbody":{"enabled":true,"type":"static","mass":1,"linearDamping":0,"angularDamping":0,"linearFactor":[1,1,1],"angularFactor":[1,1,1],"friction":1,"restitution":0},"collision":{"enabled":true,"type":"compound","halfExtents":[0.5,0.5,0.5],"radius":0.5,"axis":1,"height":2,"asset":null,"renderAsset":null}},"template_id":95947498,"template_ent_ids":{"26ee7d94-64d6-4a90-8951-a7b5f1db6e9d":"41e23152-f452-45c7-abef-1a555b5b6ee8","c621cce9-2059-4dca-a681-b541929dab08":"2318d3a1-e9f3-48ed-bb17-b386f69e01d1"}},"c621cce9-2059-4dca-a681-b541929dab08":{"name":"collision","tags":[],"enabled":true,"resource_id":"c621cce9-2059-4dca-a681-b541929dab08","parent":"26ee7d94-64d6-4a90-8951-a7b5f1db6e9d","children":[],"position":[0,0.5,0],"rotation":[0,0,0],"scale":[1,1,1],"components":{"collision":{"enabled":true,"type":"box","halfExtents":[0.5,0.5,0.5],"radius":0.5,"axis":1,"height":2,"asset":null,"renderAsset":null}}},"1186fffd-d8a0-4b86-8ac3-5bd60722e0da":{"name":"collision","tags":[],"enabled":true,"resource_id":"1186fffd-d8a0-4b86-8ac3-5bd60722e0da","parent":"8384db28-c61c-45b6-b6fa-858a471a14ce","children":[],"position":[0,0,0],"rotation":[0,0,0],"scale":[1,1,1],"components":{"collision":{"enabled":true,"type":"box","halfExtents":[2,0,2],"radius":0.5,"axis":1,"height":2,"asset":null,"renderAsset":null}}},"126f4838-072c-46f0-8c53-b539d7c94d8f":{"name":"MatchHandler","tags":[],"enabled":true,"resource_id":"126f4838-072c-46f0-8c53-b539d7c94d8f","parent":"ad67de32-0ddc-48f6-bb26-745066fee847","children":[],"position":[0,0,0],"rotation":[0,0,0],"scale":[1,1,1],"components":{"script":{"enabled":true,"order":["matchHandler","inputManager","objectManager"],"scripts":{"matchHandler":{"enabled":true,"attributes":{"matchName":"house"}},"inputManager":{"enabled":false,"attributes":{"raycastCamera":"54d33b96-8f6e-4049-a2f2-820a548b571b","inputTarget":null}},"objectManager":{"enabled":true,"attributes":{"item_config":[{"price":10,"item":95946170},{"price":20,"item":95947498},{"price":10,"item":95947455},{"price":10,"item":96466774},{"price":10,"item":96466799},{"price":10,"item":96466802},{"price":10,"item":96466803},{"price":10,"item":96466805},{"price":10,"item":96466806},{"price":10,"item":96704128}]}}}}}},"db0aa378-f896-4c25-8e05-367e6d3a3bae":{"name":"DataReference","tags":["data_ref"],"enabled":true,"resource_id":"db0aa378-f896-4c25-8e05-367e6d3a3bae","parent":"ad67de32-0ddc-48f6-bb26-745066fee847","children":[],"position":[0,0,0],"rotation":[0,0,0],"scale":[1,1,1],"components":{"script":{"enabled":true,"order":["dataRef"],"scripts":{"dataRef":{"enabled":true,"attributes":{"select_char":[{"model":96083122},{"model":96083128},{"model":93648580},{"model":96083136},{"model":96083226},{"model":96083227},{"model":96083355},{"model":96083385},{"model":96083316},{"model":96083348},{"model":95942106},{"model":95942102},{"model":95942107},{"model":95942084},{"model":95942082},{"model":95942100},{"model":95942083},{"model":95942098},{"model":96083396}]}}}}}}},"created":"2022-08-01T08:51:27.911Z","id":1488900}